odoo10_addon_website_form_metadata-10.0.1.0.0-py2.7-nspkg.pth
odoo/addons/website_form_metadata/README.rst
odoo/addons/website_form_metadata/__init__.py
odoo/addons/website_form_metadata/__manifest__.py
odoo/addons/website_form_metadata/models/__init__.py
odoo/addons/website_form_metadata/models/website_config_settings.py
odoo/addons/website_form_metadata/views/res_config_view.xml
odoo10_addon_website_form_metadata-10.0.1.0.0.dist-info/DESCRIPTION.rst
odoo10_addon_website_form_metadata-10.0.1.0.0.dist-info/METADATA
odoo10_addon_website_form_metadata-10.0.1.0.0.dist-info/RECORD
odoo10_addon_website_form_metadata-10.0.1.0.0.dist-info/WHEEL
odoo10_addon_website_form_metadata-10.0.1.0.0.dist-info/metadata.json
odoo10_addon_website_form_metadata-10.0.1.0.0.dist-info/namespace_packages.txt
odoo10_addon_website_form_metadata-10.0.1.0.0.dist-info/top_level.txt
